__init__.py
interception/__init__.py
interception/_interception.cp313-win_amd64.pyd
interception/_interception.pyi
interception/_utils.cp313-win_amd64.pyd
interception/_utils.pyi
interception/py.typed
interception/utils.py
interception/samples/__init__.py
interception/samples/__main__.py
interception/samples/axes.py
interception/samples/cadstop.py
interception/samples/caps2esc.py
interception/samples/hardwareid.py
interception/samples/identify.py
interception/samples/mathpointer.py
interception/samples/x2y.py
interception-0.6.0.dist-info/licenses/LICENSE
interception-0.6.0.dist-info/METADATA
interception-0.6.0.dist-info/WHEEL
interception-0.6.0.dist-info/top_level.txt
interception-0.6.0.dist-info/RECORD
