Metadata-Version: 2.4
Name: interception
Version: 0.6.0
Summary: interception cffi bindings
Author-email: Vasiliy Poverennov <vasiliy@poverennov.com>
License-Expression: LGPL-3.0-or-later
Classifier: Development Status :: 2 - Pre-Alpha
Classifier: Intended Audience :: Developers
Classifier: Operating System :: Microsoft :: Windows
Classifier: Programming Language :: Python
Classifier: Programming Language :: Python :: 3
Requires-Python: >=3.9
License-File: LICENSE
Requires-Dist: cffi>=1.17.1
Dynamic: license-file
